vima_sync/__init__.py
vima_sync/cli.py
vima_sync/export_csv.py
vima_sync/export_ics.py
vima_sync/load.py
vima_sync/location.py
vima_sync/normalize.py
vima_sync-0.1.0.dist-info/licenses/LICENSE
vima_sync-0.1.0.dist-info/METADATA
vima_sync-0.1.0.dist-info/WHEEL
vima_sync-0.1.0.dist-info/entry_points.txt
vima_sync-0.1.0.dist-info/top_level.txt
vima_sync-0.1.0.dist-info/RECORD
