Metadata-Version: 2.4
Name: vima-sync
Version: 0.1.0
Summary: Export Vima Run data from iOS backups to CSV and calendar
Author: John Ward
Requires-Python: >=3.10
License-File: LICENSE
Requires-Dist: pandas
Requires-Dist: pytz
Requires-Dist: ics
Requires-Dist: requests
Dynamic: license-file
